Metadata-Version: 2.1
Name: nc2480
Version: 0.2.3
Summary: python ncurses 24x80 tui goodies
Home-page: https://github.com/mdcb/python-nc2480
Author: Matthieu Bec
Author-email: mdcb808@gmail.com
License: GPL-3.0
Classifier: Intended Audience :: Science/Research
Classifier: License :: OSI Approved :: GNU General Public License v3 or later (GPLv3+)
Classifier: Operating System :: POSIX :: Linux
Classifier: Programming Language :: Python :: 3
License-File: LICENSE
